Tests/__init__.py
Tests/test_translator.py
sdk-translator/__init__.py
sdk-translator/translator.py
sheng_dholuo_translator/__init__.py
sheng_dholuo_translator/phrases.csv
sheng_dholuo_translator/translator.py
sheng_dholuo_translator-0.1.0.dist-info/METADATA
sheng_dholuo_translator-0.1.0.dist-info/WHEEL
sheng_dholuo_translator-0.1.0.dist-info/entry_points.txt
sheng_dholuo_translator-0.1.0.dist-info/top_level.txt
sheng_dholuo_translator-0.1.0.dist-info/RECORD
