Metadata-Version: 2.4
Name: sheng-dholuo-translator
Version: 0.1.0
Summary: A cultural nuance translator for Sheng and Dholuo with AI support
Home-page: https://github.com/KevinJr20/SDL-translator.git
Author: Kevin Ochieng Omondi
Author-email: your.email@example.com
Classifier: Programming Language :: Python :: 3
Classifier: License :: OSI Approved :: MIT License
Classifier: Operating System :: OS Independent
Requires-Dist: pandas
Requires-Dist: colorama
Requires-Dist: fuzzywuzzy
Requires-Dist: transformers
Requires-Dist: torch
Requires-Dist: datasets
Requires-Dist: sentencepiece
Dynamic: author
Dynamic: author-email
Dynamic: classifier
Dynamic: description
Dynamic: description-content-type
Dynamic: home-page
Dynamic: requires-dist
Dynamic: summary
